[{"title":"colossal squids","ht:approx_traffic":"1000+","description":"","link":"https://trends.google.com/trending/rss?geo=PK","pubDate":"Thu, 17 Apr 2025 22:10:00 -0700","ht:picture":"https://encrypted-tbn2.gstatic.com/images?q=tbn:ANd9GcSNlg40vIXEyQzYU8GTSvZAam9KEuODS9yLqKb0lpn7Ll4Gpht3xX2msdr9M8I","ht:picture_source":"BBC","ht:news_item":[{"ht:news_item_title":"Colossal squid filmed by scientists for first time in ocean","ht:news_item_snippet":"","ht:news_item_url":"https://www.bbc.com/news/articles/c99pg13yv32o","ht:news_item_picture":"https://encrypted-tbn2.gstatic.com/images?q=tbn:ANd9GcSNlg40vIXEyQzYU8GTSvZAam9KEuODS9yLqKb0lpn7Ll4Gpht3xX2msdr9M8I","ht:news_item_source":"BBC"},{"ht:news_item_title":"Colossal squid resembles a ‘glass sculpture’ in first footage taken from the deep sea","ht:news_item_snippet":"","ht:news_item_url":"https://www.cnn.com/2025/04/16/science/colossal-squid-footage/index.html","ht:news_item_picture":"https://encrypted-tbn2.gstatic.com/images?q=tbn:ANd9GcQ8VwUyXg7WVBtsfMfdya3LukegGdk759nPXs5lI-mDUqxuJygho9Sz_NKUTLw","ht:news_item_source":"CNN"},{"ht:news_item_title":"Deep-Sea First: See Video Of A Colossal Squid","ht:news_item_snippet":"","ht:news_item_url":"https://weather.com/news/news/2025-04-16-scientists-record-first-ever-video-of-colossal-squid-in-deep-sea","ht:news_item_picture":"https://encrypted-tbn3.gstatic.com/images?q=tbn:ANd9GcR_7ELGk5hy2a-Nv_0aoRBaZ3UqCBIJHxD08cE7jZ70k7qgYfAg2Qt83mHcPPk","ht:news_item_source":"The Weather Channel"}]},{"title":"the sandman","ht:approx_traffic":"500+","description":"","link":"https://trends.google.com/trending/rss?geo=PK","pubDate":"Thu, 17 Apr 2025 19:20:00 -0700","ht:picture":"https://encrypted-tbn1.gstatic.com/images?q=tbn:ANd9GcSINIuHagMi9G97Y4BWBGFNpudT07ojdjW6H8NmJ7-3QcnU9FZo0VnXYf4grFc","ht:picture_source":"Yahoo Home","ht:news_item":[{"ht:news_item_title":"Netflix Finally Confirms Release Dates For Popular Fantasy Series Amid Controversy","ht:news_item_snippet":"","ht:news_item_url":"https://www.yahoo.com/entertainment/articles/netflix-finally-confirms-release-dates-182230546.html","ht:news_item_picture":"https://encrypted-tbn1.gstatic.com/images?q=tbn:ANd9GcSINIuHagMi9G97Y4BWBGFNpudT07ojdjW6H8NmJ7-3QcnU9FZo0VnXYf4grFc","ht:news_item_source":"Yahoo Home"},{"ht:news_item_title":"‘The Sandman’ Sets Release Dates for Two-Part Final Season at Netflix, First Teaser Revealed","ht:news_item_snippet":"","ht:news_item_url":"https://variety.com/2025/tv/news/the-sandman-season-2-release-date-teaser-final-episodes-1236371155/","ht:news_item_picture":"https://encrypted-tbn1.gstatic.com/images?q=tbn:ANd9GcSrDYSZNeQWafnZgtaNknrBivV1JVgs2q2KimkRU3TJhcpC3ddvjwVjS7x3Vc4","ht:news_item_source":"Variety"},{"ht:news_item_title":"'The Sandman' previews final season with release date in wake of Neil Gaiman sexual assault allegations","ht:news_item_snippet":"","ht:news_item_url":"https://ew.com/the-sandman-final-season-first-look-after-neil-gaiman-assault-allegations-11716930","ht:news_item_picture":"https://encrypted-tbn2.gstatic.com/images?q=tbn:ANd9GcTkiG8Amp56nFsQQYAigKN3z_c5aTUMlMtECLJHmg2QjQ7CXv7H6O00ySA5BWs","ht:news_item_source":"Entertainment Weekly"}]},{"title":"neeraj chopra","ht:approx_traffic":"200+","description":"","link":"https://trends.google.com/trending/rss?geo=PK","pubDate":"Thu, 17 Apr 2025 19:10:00 -0700","ht:picture":"https://encrypted-tbn1.gstatic.com/images?q=tbn:ANd9GcQ59Oip-DiCroGHfTGKH-YNIGECYRbNf6OZ8SINR97QSliEQ62Pnkw3ekBC4_E","ht:picture_source":"India Today","ht:news_item":[{"ht:news_item_title":"Watch: Neeraj Chopra begins 2025 season with winning throw at South Africa event","ht:news_item_snippet":"","ht:news_item_url":"https://www.indiatoday.in/sports/athletics/story/neeraj-chopra-throw-2025-potch-invitational-event-south-africa-2710249-2025-04-17","ht:news_item_picture":"https://encrypted-tbn1.gstatic.com/images?q=tbn:ANd9GcQ59Oip-DiCroGHfTGKH-YNIGECYRbNf6OZ8SINR97QSliEQ62Pnkw3ekBC4_E","ht:news_item_source":"India Today"},{"ht:news_item_title":"Chopra, Tebogo, Kerr and Barshim confirmed for Doha","ht:news_item_snippet":"","ht:news_item_url":"https://worldathletics.org/competitions/diamond-league/news/chopra-tebogo-kerr-barshim-doha-meeting-2025","ht:news_item_picture":"https://encrypted-tbn2.gstatic.com/images?q=tbn:ANd9GcQ0Kktda8qxidvvQHLq0OTvBODac-68OPAUkxuZa58lM0mCwin0LZdya-dmdDs","ht:news_item_source":"worldathletics.org"},{"ht:news_item_title":"Sports Highlights, April 17: Neeraj Chopra Kicks Off 2025 Season With Victory In South Africa; Arsenal Knock Out Real Madrid In UCL","ht:news_item_snippet":"","ht:news_item_url":"https://www.outlookindia.com/sports/world-april-17-2025-live-blog-scores-updates-results","ht:news_item_picture":"https://encrypted-tbn3.gstatic.com/images?q=tbn:ANd9GcQI0OMoxToLCQcwEpQMT968IKpFmSS4IeAD64YRqhHpbrR01_8eZt72RjPvubQ","ht:news_item_source":"Outlook India"}]},{"title":"weather","ht:approx_traffic":"100000+","description":"","link":"https://trends.google.com/trending/rss?geo=PK","pubDate":"Thu, 17 Apr 2025 18:50:00 -0700","ht:picture":"https://encrypted-tbn0.gstatic.com/images?q=tbn:ANd9GcTZwQsUG-wKlDX0w18dPPM3OP2VViJPVsoqIEeXOvGok30pATjNO2iX40C2R6A","ht:picture_source":"The Weather Channel","ht:news_item":[{"ht:news_item_title":"Severe Weather, Flooding Rain Threats In The Plains, Midwest And South To Last Through Easter Weekend","ht:news_item_snippet":"","ht:news_item_url":"https://weather.com/storms/severe/news/2025-04-14-severe-weather-forecast-returning-threat-plains-south-midwest","ht:news_item_picture":"https://encrypted-tbn0.gstatic.com/images?q=tbn:ANd9GcTZwQsUG-wKlDX0w18dPPM3OP2VViJPVsoqIEeXOvGok30pATjNO2iX40C2R6A","ht:news_item_source":"The Weather Channel"},{"ht:news_item_title":"Severe storms threaten large parts of U.S. over Easter weekend","ht:news_item_snippet":"","ht:news_item_url":"https://www.nbcnews.com/weather/storms/severe-storms-threaten-large-parts-us-easter-weekend-rcna201714","ht:news_item_picture":"https://encrypted-tbn1.gstatic.com/images?q=tbn:ANd9GcSKNyKG_UCeD8bi8Gb-HDM-GEuuRpKBPT-idcsu1pb0awGj-1_6zWiB4ZF8Eyo","ht:news_item_source":"NBC News"},{"ht:news_item_title":"Severe storms, tornado threat to stretch across a dozen states through Easter","ht:news_item_snippet":"","ht:news_item_url":"https://www.yahoo.com/news/severe-storms-tornado-threat-stretch-185026788.html","ht:news_item_picture":"https://encrypted-tbn2.gstatic.com/images?q=tbn:ANd9GcT3agzsyKhb7PKEwq0bCEm5ANzp-sKc2kwdZ-Fb1OC_0zjEkbXIBTZjG48RvPI","ht:news_item_source":"Yahoo Home"}]},{"title":"sikandar box office collection day 19","ht:approx_traffic":"500+","description":"","link":"https://trends.google.com/trending/rss?geo=PK","pubDate":"Thu, 17 Apr 2025 18:50:00 -0700","ht:picture":"https://encrypted-tbn0.gstatic.com/images?q=tbn:ANd9GcTtYYpg_SLKZi3WO4xFCID0fp1rt6rIy8NLIGRqo00O1Wp6EzOnv8x9fLF-O_o","ht:picture_source":"Hindustan Times","ht:news_item":[{"ht:news_item_title":"Jaat worldwide box office day 7: Sunny Deol film remains steady, collects ₹76 crore","ht:news_item_snippet":"","ht:news_item_url":"https://www.hindustantimes.com/entertainment/bollywood/jaat-worldwide-box-office-day-7-sunny-deol-film-remains-steady-collects-76-crore-101744895263958.html","ht:news_item_picture":"https://encrypted-tbn0.gstatic.com/images?q=tbn:ANd9GcTtYYpg_SLKZi3WO4xFCID0fp1rt6rIy8NLIGRqo00O1Wp6EzOnv8x9fLF-O_o","ht:news_item_source":"Hindustan Times"},{"ht:news_item_title":"Sikandar Box Office Collection Day 18: Salman Khan's Film Continues To Struggle","ht:news_item_snippet":"","ht:news_item_url":"https://www.ndtv.com/entertainment/sikandar-box-office-collection-day-18-salman-khan-s-movie-makes-14-lakh-8184713","ht:news_item_picture":"https://encrypted-tbn2.gstatic.com/images?q=tbn:ANd9GcR3QYyCl36nyjaEY0w9lndJNZSdsaML46THfiQvpEIQQ0QaJyn7lqqcwz5dRvw","ht:news_item_source":"NDTV"},{"ht:news_item_title":"‘Sikandar’ Box Office Collection Day 19: Salman Khan starrer struggles to cross Rs.110 crore mark by Good","ht:news_item_snippet":"","ht:news_item_url":"https://timesofindia.indiatimes.com/entertainment/hindi/bollywood/box-office/sikandar-box-office-collection-day-19-salman-khan-starrer-struggles-to-cross-rs-110-crore-mark-by-good-friday-as-akshay-kumars-kesari-chapter-2-hits-the-screens/articleshow/120397640.cms","ht:news_item_picture":"https://encrypted-tbn1.gstatic.com/images?q=tbn:ANd9GcTjDh3il8EjWQRXnpQIyPeJyruPPU1A5Xg6I2nO4XRsD4hw8o8ZGVF7LxR9z2A","ht:news_item_source":"Times of India"}]},{"title":"ranveer allahbadia","ht:approx_traffic":"200+","description":"","link":"https://trends.google.com/trending/rss?geo=PK","pubDate":"Thu, 17 Apr 2025 18:20:00 -0700","ht:picture":"https://encrypted-tbn0.gstatic.com/images?q=tbn:ANd9GcSzPEwnut7LHkxfyrQaZwBxCIi9yFyiUNXBiJ9kdV2u3jJTJAo2v71sRn8Gtfg","ht:picture_source":"The Express Tribune","ht:news_item":[{"ht:news_item_title":"Ranveer Allahbadia says Samay Raina ‘will be back’ amid ‘India’s Got Latent’ probe","ht:news_item_snippet":"","ht:news_item_url":"https://tribune.com.pk/story/2540494/ranveer-allahbadia-says-samay-raina-will-be-back-amid-indias-got-latent-probe","ht:news_item_picture":"https://encrypted-tbn0.gstatic.com/images?q=tbn:ANd9GcSzPEwnut7LHkxfyrQaZwBxCIi9yFyiUNXBiJ9kdV2u3jJTJAo2v71sRn8Gtfg","ht:news_item_source":"The Express Tribune"},{"ht:news_item_title":"All 5 panellists of 'India's Got Latent' appear before Maha Police | The controversy first erupted in February | Inshorts","ht:news_item_snippet":"","ht:news_item_url":"https://inshorts.com/en/news/all-5-panellists-of--india-s-got-latent--appear-before-maha-police-1744735072409","ht:news_item_picture":"https://encrypted-tbn1.gstatic.com/images?q=tbn:ANd9GcRrOtJMyPUcslEAprSdNTZqbyXzDMmLQWnC7DPUVURLOpB438PO7898kkFpxvw","ht:news_item_source":"Inshorts"},{"ht:news_item_title":"Ranveer Allahbadia faces chargesheet in obscenity case as cyber police conclude probe today: Here's a timeline of the controversy","ht:news_item_snippet":"","ht:news_item_url":"https://gulfnews.com/entertainment/ranveer-allahbadia-faces-chargesheet-in-obscenity-case-as-cyber-police-conclude-probe-today-heres-a-timeline-of-the-controversy-1.500095811","ht:news_item_picture":"https://encrypted-tbn1.gstatic.com/images?q=tbn:ANd9GcTC0-iAw96E3sbw6QWxzJgPIBL0t-a54pzx0exhBnTuSyPp2-v991kenL-h5lk","ht:news_item_source":"Gulf News"}]},{"title":"you","ht:approx_traffic":"100+","description":"","link":"https://trends.google.com/trending/rss?geo=PK","pubDate":"Thu, 17 Apr 2025 18:10:00 -0700","ht:picture":"https://encrypted-tbn2.gstatic.com/images?q=tbn:ANd9GcSa0yo6Da_2juA5lA1D7lPtcPh3S6Jm6unwKkHWHSQuS-isq-imrlBYaCoFQbQ","ht:picture_source":"NFL.com","ht:news_item":[{"ht:news_item_title":"NFL legends, active players to announce selections at 2025 NFL Draft","ht:news_item_snippet":"","ht:news_item_url":"https://www.nfl.com/news/nfl-legends-active-players-to-announce-selections-at-2025-nfl-draft","ht:news_item_picture":"https://encrypted-tbn2.gstatic.com/images?q=tbn:ANd9GcSa0yo6Da_2juA5lA1D7lPtcPh3S6Jm6unwKkHWHSQuS-isq-imrlBYaCoFQbQ","ht:news_item_source":"NFL.com"},{"ht:news_item_title":"Mailbag: Would you draft TE Tyler Warren?","ht:news_item_snippet":"","ht:news_item_url":"https://www.dallascowboys.com/news/mailbag-would-you-draft-te-tyler-warren","ht:news_item_picture":"https://encrypted-tbn1.gstatic.com/images?q=tbn:ANd9GcTsWhzsUHXbLCAWt1zZhILrd3UAUKt9sTGyDg2syad8bRyzYsZoY3NQ28SMJvs","ht:news_item_source":"Dallas Cowboys"},{"ht:news_item_title":"2025 NFL Draft position rankings: TE1 is between Colston Loveland and Tyler Warren","ht:news_item_snippet":"","ht:news_item_url":"https://sports.yahoo.com/nfl/article/2025-nfl-draft-position-rankings-te1-is-between-colston-loveland-and-tyler-warren-202830540.html","ht:news_item_picture":"https://encrypted-tbn2.gstatic.com/images?q=tbn:ANd9GcQCFd_L98ek0QWz9BebwANWZBxriXNrPj-0Zg0LintF1anUiATgwcmc5BRhh3g","ht:news_item_source":"Yahoo Sports"}]},{"title":"dirham to pkr","ht:approx_traffic":"100+","description":"","link":"https://trends.google.com/trending/rss?geo=PK","pubDate":"Thu, 17 Apr 2025 15:30:00 -0700","ht:picture":"https://encrypted-tbn3.gstatic.com/images?q=tbn:ANd9GcRxnfwPspe3fojEFOtzPIWy1wt7kMLrBYbiaCvpadqPwqmTl0hTVcrXxhTL1Nw","ht:picture_source":"ARY News","ht:news_item":[{"ht:news_item_title":"UAE Dirham to Pakistani Rupee Rate Today- April 17, 2025","ht:news_item_snippet":"","ht:news_item_url":"https://arynews.tv/uae-dirham-to-pakistani-rupee-rate-today-april-17-2025/","ht:news_item_picture":"https://encrypted-tbn3.gstatic.com/images?q=tbn:ANd9GcRxnfwPspe3fojEFOtzPIWy1wt7kMLrBYbiaCvpadqPwqmTl0hTVcrXxhTL1Nw","ht:news_item_source":"ARY News"},{"ht:news_item_title":"Dirham steady at PKR 76.37, boosts remittance outlook","ht:news_item_snippet":"","ht:news_item_url":"https://www.nation.com.pk/16-Apr-2025/dirham-steady-at-pkr-76-37-boosts-remittance-outlook","ht:news_item_picture":"https://encrypted-tbn0.gstatic.com/images?q=tbn:ANd9GcS_lJUKBPCc0pOTaYobCzEI24WN8h2bc4ZjEMOk5S1SV3KmMT-lNqBYKF2-gUc","ht:news_item_source":"The Nation"},{"ht:news_item_title":"UAE Dirham suffers losses against Pak rupee today in Pakistan – 17 April 2025","ht:news_item_snippet":"","ht:news_item_url":"https://pakobserver.net/uae-dirham-suffers-losses-against-pak-rupee-today-in-pakistan-17-april-2025/","ht:news_item_picture":"https://encrypted-tbn3.gstatic.com/images?q=tbn:ANd9GcQgPzOs2A70nU8yWGWNme7EnoJVjFZREzCNtSn2aNh4CF4hl4y0dv_z_aRuaUo","ht:news_item_source":"Pakistan Observer"}]},{"title":"lazio vs bodø/glimt","ht:approx_traffic":"100+","description":"","link":"https://trends.google.com/trending/rss?geo=PK","pubDate":"Thu, 17 Apr 2025 14:50:00 -0700","ht:picture":"https://encrypted-tbn0.gstatic.com/images?q=tbn:ANd9GcRK3rr44ZkGsYRiYG0uYyJtDwXZicBi5wPIicAc26U6UHYpThem1hOzMGEzJbM","ht:picture_source":"BBC","ht:news_item":[{"ht:news_item_title":"Lazio 3-1 Bodo/Glimt (agg 3-3, 2-3 on pens): Norwegians reach first European semi-final","ht:news_item_snippet":"","ht:news_item_url":"https://www.bbc.com/sport/football/live/c2de0597y1wt","ht:news_item_picture":"https://encrypted-tbn0.gstatic.com/images?q=tbn:ANd9GcRK3rr44ZkGsYRiYG0uYyJtDwXZicBi5wPIicAc26U6UHYpThem1hOzMGEzJbM","ht:news_item_source":"BBC"},{"ht:news_item_title":"Can Taty Castellanos Inspire a Second-leg Comeback and Restore Faith of Biancocelesti?","ht:news_item_snippet":"","ht:news_item_url":"https://www.yardbarker.com/soccer/articles/can_taty_castellanos_inspire_a_second_leg_comeback_and_restore_faith_of_biancocelesti/s1_16487_42064780","ht:news_item_picture":"https://encrypted-tbn0.gstatic.com/images?q=tbn:ANd9GcRpKzzs39duKqI4tVmALJ26OsYHlrlaYWywQLqTe-V3az_XNFwkAlAYcu1O-Po","ht:news_item_source":"Yardbarker"},{"ht:news_item_title":"Baroni: ‘Lazio have no margin for error, trust in Pedro’","ht:news_item_snippet":"","ht:news_item_url":"https://football-italia.net/baroni-lazio-no-margin-for-error-trust-pedro/","ht:news_item_picture":"https://encrypted-tbn3.gstatic.com/images?q=tbn:ANd9GcSGKXfwrXQavVRD-DeA5IXqiHLonfq0ccmvPjudzIVh_Kmdhtr0PKRL44YFzyc","ht:news_item_source":"Football Italia"}]},{"title":"uefa","ht:approx_traffic":"100+","description":"","link":"https://trends.google.com/trending/rss?geo=PK","pubDate":"Thu, 17 Apr 2025 14:30:00 -0700","ht:picture":"https://encrypted-tbn1.gstatic.com/images?q=tbn:ANd9GcQbxs3pyxMqBSKO74GWS6ASoO8-jVCnhYHBcxvFifHYZPiZAASDejaCtGjERlM","ht:picture_source":"Hürriyet","ht:news_item":[{"ht:news_item_title":"Dünya futbol tarihine geçen maçta Manchester United mucizeyi yaşadı! Uzatmalarda tam 5 gol","ht:news_item_snippet":"","ht:news_item_url":"https://www.hurriyet.com.tr/sporarena/dunya-futbol-tarihine-gecen-macta-manchester-united-mucizeyi-yasadi-uzatmalarda-tam-5-gol-42768300","ht:news_item_picture":"https://encrypted-tbn1.gstatic.com/images?q=tbn:ANd9GcQbxs3pyxMqBSKO74GWS6ASoO8-jVCnhYHBcxvFifHYZPiZAASDejaCtGjERlM","ht:news_item_source":"Hürriyet"},{"ht:news_item_title":"Avrupa Ligi. \"Athletic\" ve \"Tottenham\" yarı finale yükseldi (video)","ht:news_item_snippet":"","ht:news_item_url":"https://zamin.uz/tr/spor/148077-avrupa-ligi-athletic-ve-tottenham-yar-finale-yukseldi-video.html","ht:news_item_picture":"https://encrypted-tbn1.gstatic.com/images?q=tbn:ANd9GcTk7mtvhiJ0mqqeuk5BK5mRVnmddd-MvSaUJ5qI-bg1_o7uUB1EvcgImozwnoY","ht:news_item_source":"Zamin.uz"},{"ht:news_item_title":"UEFA Avrupa Ligi'nde yarı final eşleşmeleri belli oldu","ht:news_item_snippet":"","ht:news_item_url":"https://www.ntvspor.net/futbol/uefa-avrupa-ligi-nde-yari-final-eslesmeleri-belli-oldu-6801ddf4160ea203f17b04c8","ht:news_item_picture":"https://encrypted-tbn0.gstatic.com/images?q=tbn:ANd9GcS9v0q01kLoqplvSwAI7SPRc2iqJj-MoOubvbHZrPAorQpoodsCN0Ywa1v4tp8","ht:news_item_source":"NTVSpor"}]}]