[{"title":"이일화","ht:approx_traffic":"500+","description":"","link":"https://trends.google.com/trending/rss?geo=KR","pubDate":"Fri, 26 Dec 2025 21:10:00 -0800","ht:picture":"https://encrypted-tbn2.gstatic.com/images?q=tbn:ANd9GcSvV4e2ll-unBLLFRxdmgb6s_6_KfNg9GgkQo2qPT1RQdCFt31dd3XetFDlF0M","ht:picture_source":"Daum","ht:news_item":[{"ht:news_item_title":"나영석 PD, 또 시청자 불만 폭주했다…\"자기가 연예인인가\" 선 넘은 분량 뭇매 [TEN스타필드]","ht:news_item_snippet":"","ht:news_item_url":"https://v.daum.net/v/20251227080302652","ht:news_item_picture":"https://encrypted-tbn2.gstatic.com/images?q=tbn:ANd9GcSvV4e2ll-unBLLFRxdmgb6s_6_KfNg9GgkQo2qPT1RQdCFt31dd3XetFDlF0M","ht:news_item_source":"Daum"},{"ht:news_item_title":"\"보검이는 거짓말 안 해\"…박보검, '시대의 양심' 압박에 솔직 고백 [응답하라 1988 10주년]","ht:news_item_snippet":"","ht:news_item_url":"https://news.nate.com/view/20251227n03688","ht:news_item_picture":"https://encrypted-tbn3.gstatic.com/images?q=tbn:ANd9GcTW9l9QCA4XkUxjjc1Mw0JrB7FMT_evToGvX_OcxbsqogEjZ24weuJo3JjPg3E","ht:news_item_source":"네이트"},{"ht:news_item_title":"류준열 없는 ‘응답하라 1988 10주년’, 진실공방에 초토화","ht:news_item_snippet":"","ht:news_item_url":"https://www.sportsseoul.com/news/read/1573792","ht:news_item_picture":"https://encrypted-tbn0.gstatic.com/images?q=tbn:ANd9GcQuxsHpfMH9Xr93nXAHSVlQWDkbXUzxvt0sqo2p8Ky95KTXmo4UUbS3pCkz3QE","ht:news_item_source":"스포츠서울"}]},{"title":"nct 태일","ht:approx_traffic":"1000+","description":"","link":"https://trends.google.com/trending/rss?geo=KR","pubDate":"Fri, 26 Dec 2025 20:00:00 -0800","ht:picture":"https://encrypted-tbn0.gstatic.com/images?q=tbn:ANd9GcTzwtbNouZkJfuW4Je0tfdjuBTKxi8TadmhAGBnaRRYpgIhJwgSZeCC4zo_fys","ht:picture_source":"문화일보","ht:news_item":[{"ht:news_item_title":"‘외국인 여행객 성폭행’ NCT 前멤버, 징역 3년6개월 확정","ht:news_item_snippet":"","ht:news_item_url":"https://www.munhwa.com/article/11556944","ht:news_item_picture":"https://encrypted-tbn0.gstatic.com/images?q=tbn:ANd9GcTzwtbNouZkJfuW4Je0tfdjuBTKxi8TadmhAGBnaRRYpgIhJwgSZeCC4zo_fys","ht:news_item_source":"문화일보"},{"ht:news_item_title":"아이돌 그룹 NCT 출신 태일, 성폭행 혐의 실형 확정","ht:news_item_snippet":"","ht:news_item_url":"https://imnews.imbc.com/news/2025/society/article/6789040_36718.html","ht:news_item_picture":"https://encrypted-tbn2.gstatic.com/images?q=tbn:ANd9GcRh43gfOtJXg8HnQkvGGfwq-n3kxDoTnf5rVIetR72p_bufqdXEtaqAX_SBpZ8","ht:news_item_source":"MBC 뉴스"},{"ht:news_item_title":"'특수준강간' NCT 출신 태일, 징역 3년6개월 확정…대법원 상고 기각","ht:news_item_snippet":"","ht:news_item_url":"https://www.news1.kr/society/general-society/6021253","ht:news_item_picture":"https://encrypted-tbn0.gstatic.com/images?q=tbn:ANd9GcTpoIHlvGV11kXgi9IihvI7WlirxF792EzCUP-2IgA8dDRta2bIZfn1kncErPM","ht:news_item_source":"뉴스1"}]},{"title":"동아대","ht:approx_traffic":"1000+","description":"","link":"https://trends.google.com/trending/rss?geo=KR","pubDate":"Fri, 26 Dec 2025 17:00:00 -0800","ht:picture":"https://encrypted-tbn0.gstatic.com/images?q=tbn:ANd9GcSmKDz8u4MNhcDFVOeIyyAPBywnxkVVoaHyxiSjTex1n9ywsa-ftwWxxH_irBM","ht:picture_source":"부산일보사","ht:news_item":[{"ht:news_item_title":"동아대 창업지원단, ‘2025년 벤처창업 페스티벌’ 성황리 개최","ht:news_item_snippet":"","ht:news_item_url":"https://www.busan.com/view/newsunicollvill/view.php?code=2025122414192441306","ht:news_item_picture":"https://encrypted-tbn0.gstatic.com/images?q=tbn:ANd9GcSmKDz8u4MNhcDFVOeIyyAPBywnxkVVoaHyxiSjTex1n9ywsa-ftwWxxH_irBM","ht:news_item_source":"부산일보사"},{"ht:news_item_title":"부산대 창업지원단, 제4회 메카 스타트업 데이 성황리 개최","ht:news_item_snippet":"","ht:news_item_url":"https://m.joongdo.co.kr/view.php?key=20251223010008939","ht:news_item_picture":"https://encrypted-tbn1.gstatic.com/images?q=tbn:ANd9GcRGP4taHh3gd_DG5PTmooP1p0SRaYPLZriwl-buuyL0C9ehIikIEUj6_oanY5c","ht:news_item_source":"중도일보"},{"ht:news_item_title":"2025년 창업중심대학, 도전과 성장을 한자리에","ht:news_item_snippet":"","ht:news_item_url":"http://www.veritas-a.com/news/articleView.html?idxno=591184","ht:news_item_picture":"https://encrypted-tbn0.gstatic.com/images?q=tbn:ANd9GcTGCdk7CeqiUdaG6yY8xVyQGFkBJPj0mcTzXEsnDRREbToREE7a8sGzXhheRc0","ht:news_item_source":"베리타스알파"}]},{"title":"김동현","ht:approx_traffic":"200+","description":"","link":"https://trends.google.com/trending/rss?geo=KR","pubDate":"Fri, 26 Dec 2025 17:00:00 -0800","ht:picture":"https://encrypted-tbn0.gstatic.com/images?q=tbn:ANd9GcRVW7Gx-a3WA6dB3BQuN9_Kk3tOnPRpZ7ZtBms7vN-oP9oWJvlX16_mJfY4w_M","ht:picture_source":"Daum","ht:news_item":[{"ht:news_item_title":"'격투기 선수' 김동현, 불법 침입한 백발 할아버지와 1대1 대치…\"내가 다 숨 막혀\"","ht:news_item_snippet":"","ht:news_item_url":"https://v.daum.net/v/20251226114752839","ht:news_item_picture":"https://encrypted-tbn0.gstatic.com/images?q=tbn:ANd9GcRVW7Gx-a3WA6dB3BQuN9_Kk3tOnPRpZ7ZtBms7vN-oP9oWJvlX16_mJfY4w_M","ht:news_item_source":"Daum"},{"ht:news_item_title":"'격투기 선수' 김동현, 불법 침입한 백발 할아버지와 1대1 대치…\"내가 다 숨 막혀\"","ht:news_item_snippet":"","ht:news_item_url":"https://v.daum.net/v/20251226114752839?f=p","ht:news_item_picture":"https://encrypted-tbn0.gstatic.com/images?q=tbn:ANd9GcRVW7Gx-a3WA6dB3BQuN9_Kk3tOnPRpZ7ZtBms7vN-oP9oWJvlX16_mJfY4w_M","ht:news_item_source":"Daum"},{"ht:news_item_title":"프로농구 LG, 시즌 첫 2차 연장 접전 끝에 KCC 꺾고 4연승","ht:news_item_snippet":"","ht:news_item_url":"https://www.newsis.com/view/NISX20251226_0003456205","ht:news_item_picture":"https://encrypted-tbn2.gstatic.com/images?q=tbn:ANd9GcSGik5kYAqtYvI76CKJm-xfpfLrI7GdXBZ1SJsd3jsD5LHqpcaLmEtaeid9-qc","ht:news_item_source":"뉴시스"}]},{"title":"ig","ht:approx_traffic":"100+","description":"","link":"https://trends.google.com/trending/rss?geo=KR","pubDate":"Fri, 26 Dec 2025 16:10:00 -0800","ht:picture":"https://encrypted-tbn2.gstatic.com/images?q=tbn:ANd9GcSYpRw3n8m02FqQWJ54XTQRHra03agrAQw7Ctxt7_eDOt569Y9SokS0sjp7JNk","ht:picture_source":"Forbes","ht:news_item":[{"ht:news_item_title":"Did Nicki Minaj Lose 10 Million Instagram Followers?","ht:news_item_snippet":"","ht:news_item_url":"https://www.forbes.com/sites/conormurray/2025/12/26/false-viral-claims-about-nicki-minaj-like-a-dis-from-rihanna-spread-after-turning-point-event/","ht:news_item_picture":"https://encrypted-tbn2.gstatic.com/images?q=tbn:ANd9GcSYpRw3n8m02FqQWJ54XTQRHra03agrAQw7Ctxt7_eDOt569Y9SokS0sjp7JNk","ht:news_item_source":"Forbes"},{"ht:news_item_title":"Nicki Minaj praises JD Vance as 'assassin' as Erika Kirk sits next to her","ht:news_item_snippet":"","ht:news_item_url":"https://www.nbcnews.com/news/us-news/nicki-minaj-praises-jd-vance-assassin-erika-kirk-sits-rcna250476","ht:news_item_picture":"https://encrypted-tbn3.gstatic.com/images?q=tbn:ANd9GcQRtzmITRiWuSDfkiQPwpORQaMZ1MmuCoWekgTAipIA1rVYFiKInt4aQ3ttpdQ","ht:news_item_source":"NBC News"},{"ht:news_item_title":"How Nicki Minaj went from Trump critic to the president’s biggest fan with her Turning Point appearance","ht:news_item_snippet":"","ht:news_item_url":"https://www.cnn.com/2025/12/22/entertainment/nicki-minaj-donald-trump-fan","ht:news_item_picture":"https://encrypted-tbn3.gstatic.com/images?q=tbn:ANd9GcSbDrRDPNoEvW-QI6baSChr2XQrBV0MFujsANmGNkGBuK410LGBRpYEY-4tZVo","ht:news_item_source":"CNN"}]},{"title":"australia vs england","ht:approx_traffic":"200+","description":"","link":"https://trends.google.com/trending/rss?geo=KR","pubDate":"Fri, 26 Dec 2025 15:50:00 -0800","ht:picture":"https://encrypted-tbn3.gstatic.com/images?q=tbn:ANd9GcQptJcISfBr0eR4eKqGQj-X2o19lS6kyJFhmo99xbkJVVds2aulr0-DoNT1Aek","ht:picture_source":"BBC","ht:news_item":[{"ht:news_item_title":"The Ashes 2025 LIVE: Australia vs England, fourth Test, Melbourne - cricket score, radio & highlights","ht:news_item_snippet":"","ht:news_item_url":"https://www.bbc.com/sport/cricket/live/cj6xrz556zwt","ht:news_item_picture":"https://encrypted-tbn3.gstatic.com/images?q=tbn:ANd9GcQptJcISfBr0eR4eKqGQj-X2o19lS6kyJFhmo99xbkJVVds2aulr0-DoNT1Aek","ht:news_item_source":"BBC"},{"ht:news_item_title":"Boxing Day Test 2025: Australia v England fourth Ashes Test, day two – live updates","ht:news_item_snippet":"","ht:news_item_url":"https://www.theguardian.com/sport/live/2025/dec/26/australia-vs-england-live-ashes-fourth-4th-test-day-two-aus-v-eng-cricket-scores-updates-mcg","ht:news_item_picture":"https://encrypted-tbn0.gstatic.com/images?q=tbn:ANd9GcRE0L9zQcoP-aDpENVMQmNf4wUJPIlAAhZHF3xuXE7J_adaoqubLXm38bN16A0","ht:news_item_source":"The Guardian"},{"ht:news_item_title":"Ball by Ball Commentary & Live Score - AUS vs ENG, 4th Test","ht:news_item_snippet":"","ht:news_item_url":"https://www.espncricinfo.com/series/the-ashes-2025-26-1455609/australia-vs-england-4th-test-1455614/ball-by-ball-commentary","ht:news_item_picture":"https://encrypted-tbn1.gstatic.com/images?q=tbn:ANd9GcTPPqdFa9rRjjpz8pPXbj8ON6A7wtwrLO4HPhFfGlFhS3g9O1Lr7Rgh52Qi2QY","ht:news_item_source":"ESPNcricinfo"}]},{"title":"이혁재","ht:approx_traffic":"100+","description":"","link":"https://trends.google.com/trending/rss?geo=KR","pubDate":"Fri, 26 Dec 2025 15:40:00 -0800","ht:picture":"https://encrypted-tbn0.gstatic.com/images?q=tbn:ANd9GcS8W6Q71NiHPvKmTie-704pCGahYDrB6wNEsCDIdXE0s_SybebhHyEFRQmWhO0","ht:picture_source":"뉴시스","ht:news_item":[{"ht:news_item_title":"개그맨 이혁재, 인천시 미디어 특보 활동 당시 사기 혐의 피소","ht:news_item_snippet":"","ht:news_item_url":"https://www.newsis.com/view/NISX20251226_0003456218","ht:news_item_picture":"https://encrypted-tbn0.gstatic.com/images?q=tbn:ANd9GcS8W6Q71NiHPvKmTie-704pCGahYDrB6wNEsCDIdXE0s_SybebhHyEFRQmWhO0","ht:news_item_source":"뉴시스"},{"ht:news_item_title":"이혁재 '인천 특보라며 3억 빌렸다?'…또 금전 문제로 경찰 조사","ht:news_item_snippet":"","ht:news_item_url":"https://www.sedaily.com/NewsView/2H1W5R3YKI","ht:news_item_picture":"https://encrypted-tbn0.gstatic.com/images?q=tbn:ANd9GcQZWTBKD0Lm0MvvDXoFxIB8x0RtxpWLdz3VsC4Y6LFg2qYw86hTQSXZsWOG4Zc","ht:news_item_source":"서울경제"},{"ht:news_item_title":"개그맨 이혁재, '3억 사기' 피소…\"사업 이권 줄게\" vs \"직함 이용 안 해\"","ht:news_item_snippet":"","ht:news_item_url":"https://news.nate.com/view/20251227n02796","ht:news_item_picture":"https://encrypted-tbn1.gstatic.com/images?q=tbn:ANd9GcSGwmDQw93rRUR51Dm2nKvzllYRlpRYJGpbm9plrlBgYYvG2rXk932dOQxgfwI","ht:news_item_source":"네이트"}]},{"title":"天氣","ht:approx_traffic":"100+","description":"","link":"https://trends.google.com/trending/rss?geo=KR","pubDate":"Fri, 26 Dec 2025 14:10:00 -0800","ht:picture":"https://encrypted-tbn0.gstatic.com/images?q=tbn:ANd9GcT8ts3F7SRGcqo-WYKCPDHT3Gc0pB4K39bL-xOrqs19W1HK3qEhm7CqV0LvMRM","ht:picture_source":"氣象應用推廣基金會","ht:news_item":[{"ht:news_item_title":"今明迎風濕冷週日起冷氣團減弱","ht:news_item_snippet":"","ht:news_item_url":"http://www.metapp.org.tw/index.php/bossweathernews/3708-2025-12-25-21-46-24","ht:news_item_picture":"https://encrypted-tbn0.gstatic.com/images?q=tbn:ANd9GcT8ts3F7SRGcqo-WYKCPDHT3Gc0pB4K39bL-xOrqs19W1HK3qEhm7CqV0LvMRM","ht:news_item_source":"氣象應用推廣基金會"},{"ht:news_item_title":"實實在在的大陸冷氣團影響 鄭明典：台北站維持14度以下 是要提醒重點","ht:news_item_snippet":"","ht:news_item_url":"https://udn.com/news/story/7266/9226708","ht:news_item_picture":"https://encrypted-tbn2.gstatic.com/images?q=tbn:ANd9GcTuEFRLC9iYfkX2bHkV6Y_SKK_eNqJuNrz45JPqP_pZzo7ili5rzMTCnkOsMs4","ht:news_item_source":"聯合新聞網"},{"ht:news_item_title":"冷氣團還在發威！2縣市跌破10度 各地早晚冷颼颼","ht:news_item_snippet":"","ht:news_item_url":"https://news.ltn.com.tw/news/life/breakingnews/5291021","ht:news_item_picture":"https://encrypted-tbn1.gstatic.com/images?q=tbn:ANd9GcRuhL1U55t4q4H2mt2PgEn_KYWtK5I0KPoDLyJ0-hLyQTBB3tt1435k61CkcQA","ht:news_item_source":"自由時報"}]},{"title":"프리미어리그","ht:approx_traffic":"1000+","description":"","link":"https://trends.google.com/trending/rss?geo=KR","pubDate":"Fri, 26 Dec 2025 13:50:00 -0800","ht:picture":"https://encrypted-tbn0.gstatic.com/images?q=tbn:ANd9GcTKHHHy7lmojvQnTgge8noGDHS3TTamteP9dkJODEHgSlJE2tG6GzPZH4LUmpM","ht:picture_source":"Daum","ht:news_item":[{"ht:news_item_title":"'이강인의 주전 경쟁 완승' 리버풀, 입지 잃은 바르콜라 영입 시도","ht:news_item_snippet":"","ht:news_item_url":"https://v.daum.net/v/20251226000103913?f=p","ht:news_item_picture":"https://encrypted-tbn0.gstatic.com/images?q=tbn:ANd9GcTKHHHy7lmojvQnTgge8noGDHS3TTamteP9dkJODEHgSlJE2tG6GzPZH4LUmpM","ht:news_item_source":"Daum"},{"ht:news_item_title":"바르셀로나 아니었나? '야말 절친' 스페인 윙어, 프리미어리그 러브콜에 \"OK\"","ht:news_item_snippet":"","ht:news_item_url":"https://news.nate.com/view/20251225n02175?mid=n1007","ht:news_item_picture":"https://encrypted-tbn1.gstatic.com/images?q=tbn:ANd9GcRELH1ReUUozfOuUB6-Wa9ZdAp6u8RXIuVdb2lsTXyzaSHQ-dD-K2tYYYMZfDw","ht:news_item_source":"네이트"},{"ht:news_item_title":"'리버풀 이적설' 02년생 '이강인 동료' 공격수, \"핵심 선수 보장 원한다\"","ht:news_item_snippet":"","ht:news_item_url":"https://m.news.zum.com/articles/103076816/%EB%A6%AC%EB%B2%84%ED%92%80-%EC%9D%B4%EC%A0%81%EC%84%A4-02%EB%85%84%EC%83%9D-%EC%9D%B4%EA%B0%95%EC%9D%B8-%EB%8F%99%EB%A3%8C-%EA%B3%B5%EA%B2%A9%EC%88%98-%ED%95%B5%EC%8B%AC-%EC%84%A0%EC%88%98-%EB%B3%B4%EC%9E%A5-%EC%9B%90%ED%95%9C%EB%8B%A4?cm=news_edit&r=4&thumb=0","ht:news_item_picture":"https://encrypted-tbn3.gstatic.com/images?q=tbn:ANd9GcSTnSX12TB7kDNcjutMH1SLcV30CV37Ut_alIdjiER32jXxdg0auRAXpqtNslU","ht:news_item_source":"ZUM 뉴스"}]},{"title":"man united vs newcastle","ht:approx_traffic":"2000+","description":"","link":"https://trends.google.com/trending/rss?geo=KR","pubDate":"Fri, 26 Dec 2025 12:20:00 -0800","ht:picture":"https://encrypted-tbn1.gstatic.com/images?q=tbn:ANd9GcROOpwRXRoccS5HgR_4zY2pBGXYBcWEmW6V07nWdZTeTgET_Qc56sQgHoTsS9s","ht:picture_source":"BBC","ht:news_item":[{"ht:news_item_title":"'We suffered together' - Amorim changes style as Man Utd win","ht:news_item_snippet":"","ht:news_item_url":"https://www.bbc.com/sport/football/articles/c4gv11reqleo","ht:news_item_picture":"https://encrypted-tbn1.gstatic.com/images?q=tbn:ANd9GcROOpwRXRoccS5HgR_4zY2pBGXYBcWEmW6V07nWdZTeTgET_Qc56sQgHoTsS9s","ht:news_item_source":"BBC"},{"ht:news_item_title":"Amorim's Tactical Shift Secures Manchester United's 1-0 Newcastle Win","ht:news_item_snippet":"","ht:news_item_url":"https://www.chosun.com/english/sports-en/2025/12/27/SBNYNHTOINCXTFXC2OSCUF4AAY/","ht:news_item_picture":"https://encrypted-tbn1.gstatic.com/images?q=tbn:ANd9GcRvYB10Ug24FXQGfUeUR1j8d1skUgr-bFqPs9olq12PUZ1H8YnMixMNiNU_jvE","ht:news_item_source":"조선일보"},{"ht:news_item_title":"Amoring of the world beat the three-back stubbornness for the first time.Manchester United won 1-0 i..","ht:news_item_snippet":"","ht:news_item_url":"https://www.mk.co.kr/en/sports/11740383","ht:news_item_picture":"https://encrypted-tbn3.gstatic.com/images?q=tbn:ANd9GcRopiBuf69eQoQyzTH9ys5v3kEElQ7DtDco_t2bajXQXZl0DwudWtEGKDpje08","ht:news_item_source":"매일경제"}]}]