[{"title":"www bbc hausa","ht:approx_traffic":"100+","description":"","link":"https://trends.google.com/trending/rss?geo=NG","pubDate":"Fri, 19 Sep 2025 22:40:00 -0700","ht:picture":"https://encrypted-tbn2.gstatic.com/images?q=tbn:ANd9GcSTxdErmok_8L2pW0D65WsQibA7Xrz0b_Iy_l0OvFb1fo542lBc8smQ-bNo3rM","ht:picture_source":"BBC","ht:news_item":[{"ht:news_item_title":"Football gossip: Kane, Anderson, Gravenberch, Saliba, Benitez","ht:news_item_snippet":"","ht:news_item_url":"https://www.bbc.com/sport/football/articles/c5y828klvmeo","ht:news_item_picture":"https://encrypted-tbn2.gstatic.com/images?q=tbn:ANd9GcSTxdErmok_8L2pW0D65WsQibA7Xrz0b_Iy_l0OvFb1fo542lBc8smQ-bNo3rM","ht:news_item_source":"BBC"},{"ht:news_item_title":"Barcelona want to sign two Bayern Munich stars","ht:news_item_snippet":"","ht:news_item_url":"https://telegrafi.com/en/Barcelona-wants-to-sign-two-Bayern-Munich-stars/","ht:news_item_picture":"https://encrypted-tbn1.gstatic.com/images?q=tbn:ANd9GcTftjIfxG1o_youa0kMVrrl7xvqqp7PPx-_TIrBF_IX-Y69fdBcVOLHu4JTSi0","ht:news_item_source":"Telegrafi"},{"ht:news_item_title":"The defender Flick wants to sign for Barça responds: Pau Cubarsí didn't expect it","ht:news_item_snippet":"","ht:news_item_url":"https://madrid-barcelona.com/en/fc-barcelona/defender-that-flick-wants-to-sign-for-barca-responds-pau-cubarsi-did-not-expect-it","ht:news_item_picture":"https://encrypted-tbn1.gstatic.com/images?q=tbn:ANd9GcSb4E4b3r0fqTDfi80anmDfB7XmPQJnSU5DyEPcKH_Fx8LPpSlfb0_QnMC0juc","ht:news_item_source":"madrid-barcelona.com"}]},{"title":"bbc hausa labaran duniya","ht:approx_traffic":"200+","description":"","link":"https://trends.google.com/trending/rss?geo=NG","pubDate":"Fri, 19 Sep 2025 22:10:00 -0700","ht:picture":"https://encrypted-tbn2.gstatic.com/images?q=tbn:ANd9GcR2SMRPgXiO_CUfwTFK2CvIoC1E8HlnIFlWLvtZo2Q6SOXz7M8X0RaN4mFblM0","ht:picture_source":"BBC","ht:news_item":[{"ht:news_item_title":"Abubuwan da ke faruwa a Najeriya da sassan duniya","ht:news_item_snippet":"","ht:news_item_url":"https://www.bbc.com/hausa/live/c4g904nv0l8t","ht:news_item_picture":"https://encrypted-tbn2.gstatic.com/images?q=tbn:ANd9GcR2SMRPgXiO_CUfwTFK2CvIoC1E8HlnIFlWLvtZo2Q6SOXz7M8X0RaN4mFblM0","ht:news_item_source":"BBC"},{"ht:news_item_title":"Abubuwan da ke faruwa a Najeriya da sassan duniya","ht:news_item_snippet":"","ht:news_item_url":"https://www.bbc.com/hausa/live/cvgv8zr9k1yt","ht:news_item_picture":"https://encrypted-tbn0.gstatic.com/images?q=tbn:ANd9GcQ7Clt08U7ITOu_sVsWBjQnf60pp3sYm9KWVJ6qC_NdmB-K_wDz03pRaxko8R4","ht:news_item_source":"BBC"},{"ht:news_item_title":"Mace ko namiji: Me ya sa ake taƙaddama kan jinsin matar shugaban Faransa?","ht:news_item_snippet":"","ht:news_item_url":"https://www.bbc.com/hausa/articles/cp3qk0rq73po","ht:news_item_picture":"https://encrypted-tbn0.gstatic.com/images?q=tbn:ANd9GcREMxhsskPMpUje67iL_fhZBWEyLrQQ0MeJ-tz6KDhR5GNNaBCZUcGIS9m53vU","ht:news_item_source":"BBC"}]},{"title":"3 body problem season 2","ht:approx_traffic":"200+","description":"","link":"https://trends.google.com/trending/rss?geo=NG","pubDate":"Fri, 19 Sep 2025 17:40:00 -0700","ht:picture":"https://encrypted-tbn0.gstatic.com/images?q=tbn:ANd9GcSkabRv7ZDv2rO8rTmWF9_6gaGTmnb-wO6H9g-Z7HN4U55ycRYJOk4Eu3pRbwU","ht:picture_source":"3DVF","ht:news_item":[{"ht:news_item_title":"Netflix’s Most Expensive Series Resurfaces, But Its Sequel Will Require Patience","ht:news_item_snippet":"","ht:news_item_url":"https://3dvf.com/en/netflixs-most-expensive-series-resurfaces-but-its-sequel-will-require-patience/","ht:news_item_picture":"https://encrypted-tbn0.gstatic.com/images?q=tbn:ANd9GcSkabRv7ZDv2rO8rTmWF9_6gaGTmnb-wO6H9g-Z7HN4U55ycRYJOk4Eu3pRbwU","ht:news_item_source":"3DVF"},{"ht:news_item_title":"Welcome News About The '3 Body Problem' Season 2 Release Date On Netflix","ht:news_item_snippet":"","ht:news_item_url":"https://www.forbes.com/sites/carolinereid/2025/09/18/welcome-news-about-the-3-body-problem-season-2-release-date-on-netflix/","ht:news_item_picture":"https://encrypted-tbn0.gstatic.com/images?q=tbn:ANd9GcTIe4xTWITRuv3OJbxxXUY2jXxWCf58XrgVajqhtD1OeWbEsrSnZxTm28SxIw4","ht:news_item_source":"Forbes"}]},{"title":"chief of war","ht:approx_traffic":"100+","description":"","link":"https://trends.google.com/trending/rss?geo=NG","pubDate":"Fri, 19 Sep 2025 16:30:00 -0700","ht:picture":"https://encrypted-tbn3.gstatic.com/images?q=tbn:ANd9GcTntRJc1DTtOFBjZWxYjEGOaQCnSYfzIS_3ndcvbMKN3Rl3Ea8oo6YOObxVJs8","ht:picture_source":"TheWrap","ht:news_item":[{"ht:news_item_title":"'Chief of War' Creators Break Down 'Epic' Season 1 Finale, Share Season 2 Hopes: 'It Only Gets Bigger'","ht:news_item_snippet":"","ht:news_item_url":"https://www.thewrap.com/chief-of-war-season-1-episode-9-jason-momoa-thomas-paa-sibbett-interview/","ht:news_item_picture":"https://encrypted-tbn3.gstatic.com/images?q=tbn:ANd9GcTntRJc1DTtOFBjZWxYjEGOaQCnSYfzIS_3ndcvbMKN3Rl3Ea8oo6YOObxVJs8","ht:news_item_source":"TheWrap"},{"ht:news_item_title":"How Chief of War Balances History & Entertainment | Aloha Authentic Episode 512","ht:news_item_snippet":"","ht:news_item_url":"https://www.khon2.com/aloha-authentic/how-chief-of-war-balances-history-entertainment-aloha-authentic-episode-512/","ht:news_item_picture":"https://encrypted-tbn3.gstatic.com/images?q=tbn:ANd9GcQXDLoSJpZ2btJY1KUVf4pTWGUjexg2Dfddc3B9HY3n7URBmaJSE9PuA07BqUI","ht:news_item_source":"KHON2"},{"ht:news_item_title":"Chief of War Ending Reveals if Jason Momoa’s Ka’iana Dies","ht:news_item_snippet":"","ht:news_item_url":"https://www.yahoo.com/entertainment/tv/articles/chief-war-ending-reveals-jason-074302414.html","ht:news_item_picture":"https://encrypted-tbn3.gstatic.com/images?q=tbn:ANd9GcRZKeaQ4Ukscoj425wGBu93__hKGwW8bu0pihzmepG9akiRKaz4ZKEu1SEaKok","ht:news_item_source":"Yahoo"}]},{"title":"upwork inc","ht:approx_traffic":"500+","description":"","link":"https://trends.google.com/trending/rss?geo=NG","pubDate":"Fri, 19 Sep 2025 15:00:00 -0700","ht:picture":"https://encrypted-tbn3.gstatic.com/images?q=tbn:ANd9GcReCij8IwTMNnGuR2H078ZkDntilmUfGDQ3hiGlK7692BLyNNJ0Vc5VSZtG2Q","ht:picture_source":"Yahoo Finance","ht:news_item":[{"ht:news_item_title":"Upwork (UPWK) Surges 8.1%: Is This an Indication of Further Gains?","ht:news_item_snippet":"","ht:news_item_url":"https://finance.yahoo.com/news/upwork-upwk-surges-8-1-163500203.html","ht:news_item_picture":"https://encrypted-tbn3.gstatic.com/images?q=tbn:ANd9GcReCij8IwTMNnGuR2H078ZkDntilmUfGDQ3hiGlK7692BLyNNJ0Vc5VSZtG2Q","ht:news_item_source":"Yahoo Finance"},{"ht:news_item_title":"Upwork Joins Elite Club Of Stocks With RS Ratings Over 90","ht:news_item_snippet":"","ht:news_item_url":"https://www.investors.com/ibd-data-stories/upwork-joins-elite-club-of-stocks-with-rs-ratings-over-90/","ht:news_item_picture":"https://encrypted-tbn0.gstatic.com/images?q=tbn:ANd9GcQyy5r7Pn5UfacjNQGKzirDC3Zomj6bwbXDdVJQUn-ts-lOXLcayCVKKqnUjNA","ht:news_item_source":"Investor's Business Daily"},{"ht:news_item_title":"Upwork stock hits 52-week high at 18.15 USD By Investing.com","ht:news_item_snippet":"","ht:news_item_url":"https://za.investing.com/news/company-news/upwork-stock-hits-52week-high-at-1815-usd-93CH-3883836","ht:news_item_picture":"https://encrypted-tbn3.gstatic.com/images?q=tbn:ANd9GcQ9UFNOjQxXlm6iFQSaxGAuVc3SfVImuiZr4AgoD6W7A9VU3qMoHYZrtttGKtA","ht:news_item_source":"Investing.com South Africa"}]},{"title":"brenda biya","ht:approx_traffic":"100+","description":"","link":"https://trends.google.com/trending/rss?geo=NG","pubDate":"Fri, 19 Sep 2025 14:40:00 -0700","ht:picture":"https://encrypted-tbn1.gstatic.com/images?q=tbn:ANd9GcQ48LyKZaVHcoZyYQ-BFXGSLYSKSh4h9woOPnMRPrPpa8KsfGQpX2VXkWlHZWE","ht:picture_source":"RFI","ht:news_item":[{"ht:news_item_title":"Présidentielle au Cameroun: Brenda Biya appelle à ne pas voter pour son père Paul Biya, dans une vidéo","ht:news_item_snippet":"","ht:news_item_url":"https://www.rfi.fr/fr/afrique/20250919-pr%C3%A9sidentielle-au-cameroun-brenda-biya-appelle-%C3%A0-ne-pas-voter-pour-son-p%C3%A8re-paul-biya-dans-une-vid%C3%A9o","ht:news_item_picture":"https://encrypted-tbn1.gstatic.com/images?q=tbn:ANd9GcQ48LyKZaVHcoZyYQ-BFXGSLYSKSh4h9woOPnMRPrPpa8KsfGQpX2VXkWlHZWE","ht:news_item_source":"RFI"},{"ht:news_item_title":"Cameroun : Présidentielle 2025, la fille du président se positionne contre la candidature de son père","ht:news_item_snippet":"","ht:news_item_url":"https://www.koaci.com/index.php/article/2025/09/19/cameroun/politique/cameroun-presidentielle-2025-la-fille-du-president-se-positionne-contre-la-candidature-de-son-pere_190321.html","ht:news_item_picture":"https://encrypted-tbn3.gstatic.com/images?q=tbn:ANd9GcTbE1RJbLGkRKQ7_OrYAcvPthNihcp-VkrSbis8pc3v73YTDrpk81vwbV6isJk","ht:news_item_source":"koaci"},{"ht:news_item_title":"Brenda Biya – Patrick Rifoe dénonce « l’exploitation à des fins politiciennes de la détresse d’une jeune femme »","ht:news_item_snippet":"","ht:news_item_url":"https://actucameroun.com/2025/09/19/brenda-biya-patrick-rifoe-denonce-lexploitation-a-des-fins-politiciennes-de-la-detresse-dune-jeune-femme/","ht:news_item_picture":"https://encrypted-tbn1.gstatic.com/images?q=tbn:ANd9GcQJvgI5vg14T-uRvzUkqMlCiDEN9iD633BVLr_p4hMepTj3n42oJJUHLnGiHw4","ht:news_item_source":"Actu Cameroun"}]},{"title":"liverpool vs everton prediction","ht:approx_traffic":"200+","description":"","link":"https://trends.google.com/trending/rss?geo=NG","pubDate":"Fri, 19 Sep 2025 14:00:00 -0700","ht:picture":"https://encrypted-tbn0.gstatic.com/images?q=tbn:ANd9GcTWAwhtSChEvgEhKMcQidnY-V43kZr6C7UCGvfonuUmhoQZe0qQ22-QoF1rnEQ","ht:picture_source":"BBC","ht:news_item":[{"ht:news_item_title":"Liverpool v Everton: Why do Toffees have belief despite Anfield nightmares?","ht:news_item_snippet":"","ht:news_item_url":"https://www.bbc.com/sport/football/articles/c4gqdwdg1dpo","ht:news_item_picture":"https://encrypted-tbn0.gstatic.com/images?q=tbn:ANd9GcTWAwhtSChEvgEhKMcQidnY-V43kZr6C7UCGvfonuUmhoQZe0qQ22-QoF1rnEQ","ht:news_item_source":"BBC"},{"ht:news_item_title":"Liverpool v Everton: Merseyside derby team news","ht:news_item_snippet":"","ht:news_item_url":"https://www.liverpoolfc.com/news/liverpool-v-everton-merseyside-derby-team-news-2","ht:news_item_picture":"https://encrypted-tbn1.gstatic.com/images?q=tbn:ANd9GcQtn38OdrxF6wfPaz5J34kpRTSURuGIoOW4Lc09fvAcCZQwkd-sV8CKgO1_n6g","ht:news_item_source":"Liverpool FC"},{"ht:news_item_title":"Liverpool vs. Everton: Preview, Predictions and Lineups","ht:news_item_snippet":"","ht:news_item_url":"https://www.si.com/soccer/liverpool-vs-everton-preview-predictions-lineups-9-20-25","ht:news_item_picture":"https://encrypted-tbn1.gstatic.com/images?q=tbn:ANd9GcQ310ypKITIQjZY3wazYcjseph0m0LmT4mm5coxxcIdkqHhfgMo6rDHBqjsIss","ht:news_item_source":"Sports Illustrated"}]},{"title":"brighton vs tottenham","ht:approx_traffic":"500+","description":"","link":"https://trends.google.com/trending/rss?geo=NG","pubDate":"Fri, 19 Sep 2025 14:00:00 -0700","ht:picture":"https://encrypted-tbn1.gstatic.com/images?q=tbn:ANd9GcSZ2wXuQ47hs4sGrbNSVRMoB615UkQDMMKvJpOfYQZ5tGU7fjnLYHhS9qqBtl4","ht:picture_source":"Sports Mole","ht:news_item":[{"ht:news_item_title":"Preview: Brighton vs Spurs - prediction, team news, lineups","ht:news_item_snippet":"","ht:news_item_url":"https://www.sportsmole.co.uk/football/brighton-and-hove-albion/preview/brighton-vs-spurs-prediction-team-news-lineups_581698.html","ht:news_item_picture":"https://encrypted-tbn1.gstatic.com/images?q=tbn:ANd9GcSZ2wXuQ47hs4sGrbNSVRMoB615UkQDMMKvJpOfYQZ5tGU7fjnLYHhS9qqBtl4","ht:news_item_source":"Sports Mole"},{"ht:news_item_title":"Tottenham XI vs Brighton: Confirmed team news, predicted lineup and injury latest for Premier League","ht:news_item_snippet":"","ht:news_item_url":"https://www.standard.co.uk/sport/football/tottenham-xi-vs-brighton-confirmed-team-news-predicted-lineup-injury-latest-premier-league-2025-b1248685.html","ht:news_item_picture":"https://encrypted-tbn3.gstatic.com/images?q=tbn:ANd9GcRmv-VjZO7gp8Hx7xaKtB2xtvSWX0r16c0mWP4SKMGGVkOSi7T3Krp2xIxqpGo","ht:news_item_source":"London Evening Standard"},{"ht:news_item_title":"The Daly Brief | Brighton vs Spurs, Premier League","ht:news_item_snippet":"","ht:news_item_url":"https://onefootball.com/en/news/the-daly-brief-brighton-vs-spurs-premier-league-41688049","ht:news_item_picture":"https://encrypted-tbn1.gstatic.com/images?q=tbn:ANd9GcSvAXQyzL_FKM5Emw7_8runmCWb7TSi11hfj-7pqfDdKofajw0amKrxBLnDcwo","ht:news_item_source":"OneFootball"}]},{"title":"estonia","ht:approx_traffic":"100+","description":"","link":"https://trends.google.com/trending/rss?geo=NG","pubDate":"Fri, 19 Sep 2025 13:50:00 -0700","ht:picture":"https://encrypted-tbn0.gstatic.com/images?q=tbn:ANd9GcQY1_solMwj2kv4CNd61H9Qkzk0xFrvjd7uRwJew7CS265SeYaRfExXPP60R4E","ht:picture_source":"BBC","ht:news_item":[{"ht:news_item_title":"Estonia seeks urgent Nato consultation after Russian jets violate airspace","ht:news_item_snippet":"","ht:news_item_url":"https://www.bbc.com/news/articles/czrp6p5mj3zo","ht:news_item_picture":"https://encrypted-tbn0.gstatic.com/images?q=tbn:ANd9GcQY1_solMwj2kv4CNd61H9Qkzk0xFrvjd7uRwJew7CS265SeYaRfExXPP60R4E","ht:news_item_source":"BBC"},{"ht:news_item_title":"Estonia, NATO slam ‘brazen’ Russian air incursion, Moscow denies claim","ht:news_item_snippet":"","ht:news_item_url":"https://www.aljazeera.com/news/2025/9/19/estonia-says-russian-fighter-jets-entered-airspace-in-brazen-intrusion","ht:news_item_picture":"https://encrypted-tbn2.gstatic.com/images?q=tbn:ANd9GcSs1q8xRhgedliuoTHwMtZhkaLO_VOb2NGyv6GQkVW68kEv7NgyLtHhOogsQ2M","ht:news_item_source":"Al Jazeera"},{"ht:news_item_title":"Nato intercepts Russian fighter jets on ‘reckless’ violation of Estonian airspace","ht:news_item_snippet":"","ht:news_item_url":"https://www.theguardian.com/world/2025/sep/19/estonia-accuses-russia-of-brazen-violation-of-its-airspace","ht:news_item_picture":"https://encrypted-tbn1.gstatic.com/images?q=tbn:ANd9GcQZJEV8-m5wtl5dOsBy1AdkeL97gU0GNMkPL5OXfEaASO4Lmt7EjCPKL2Va5j4","ht:news_item_source":"The Guardian"}]},{"title":"cagliari fc","ht:approx_traffic":"200+","description":"","link":"https://trends.google.com/trending/rss?geo=NG","pubDate":"Fri, 19 Sep 2025 13:40:00 -0700","ht:picture":"https://encrypted-tbn3.gstatic.com/images?q=tbn:ANd9GcR-7e4ONuwuLeScbPSkzdc-iXh8UQJKEuJxMQaEX3FlNpisH2eg77JE0_rrQBI","ht:picture_source":"MARCA","ht:news_item":[{"ht:news_item_title":"US Lecce - Cagliari live","ht:news_item_snippet":"","ht:news_item_url":"https://www.marca.com/en/soccer/serie-a/us-lecce-cagliari/2025/09/19/01_0107_20250919_130_124-live.html","ht:news_item_picture":"https://encrypted-tbn3.gstatic.com/images?q=tbn:ANd9GcR-7e4ONuwuLeScbPSkzdc-iXh8UQJKEuJxMQaEX3FlNpisH2eg77JE0_rrQBI","ht:news_item_source":"MARCA"},{"ht:news_item_title":"Lecce vs Cagliari Prediction: Opening Match of a Round Will End With a Draw?","ht:news_item_snippet":"","ht:news_item_url":"https://www.telecomasia.net/sports-betting/tips/football/italy-serie-a/lecce-vs-cagliari-prediction-for-the-match-on-september-19-2025/","ht:news_item_picture":"https://encrypted-tbn1.gstatic.com/images?q=tbn:ANd9GcQsnTzafCl58L82QroOV9uBY5GSXYCOREa_6sAwE2-nuG8Y49SjdtOBddQtfxw","ht:news_item_source":"Telecom Asia Sport"},{"ht:news_item_title":"Belotti double keeps Cagliari in the high life","ht:news_item_snippet":"","ht:news_item_url":"https://www.beinsports.com/en-nz/football/serie-a/articles-video/belotti-double-keeps-cagliari-in-the-high-life-2025-09-19","ht:news_item_picture":"https://encrypted-tbn0.gstatic.com/images?q=tbn:ANd9GcQP8YPKRnCvF1M4rcioayi7AzU104JKqhlqqNWmx9p-DrMbGCgTu7SBMJS-AUE","ht:news_item_source":"beIN SPORTS"}]}]